robot_image/__init__.py
robot_image/highlight_image.py
robot_image/highlight_image_main.py
robot_image/index.py
robot_image/screen_shot.py
robot_image/screen_shot_main.py
robot_image-0.3.0.dist-info/METADATA
robot_image-0.3.0.dist-info/WHEEL
robot_image-0.3.0.dist-info/RECORD
